aind_data_transfer/__init__.py
aind_data_transfer/gcs.py
aind_data_transfer/s3.py
aind_data_transfer/config_loader/__init__.py
aind_data_transfer/config_loader/base_config.py
aind_data_transfer/config_loader/ephys_configuration_loader.py
aind_data_transfer/config_loader/imaging_configuration_loader.py
aind_data_transfer/jobs/__init__.py
aind_data_transfer/jobs/basic_job.py
aind_data_transfer/jobs/s3_upload_job.py
aind_data_transfer/jobs/transcode_job.py
aind_data_transfer/jobs/zarr_upload_job.py
aind_data_transfer/jobs/cronjobs/__init__.py
aind_data_transfer/jobs/cronjobs/exaspim_cron_job.py
aind_data_transfer/jobs/cronjobs/templates/zarr_upload_job_template.sh
aind_data_transfer/readers/__init__.py
aind_data_transfer/readers/ephys_readers.py
aind_data_transfer/readers/imaging_readers.py
aind_data_transfer/transformations/__init__.py
aind_data_transfer/transformations/converters.py
aind_data_transfer/transformations/deinterleave.py
aind_data_transfer/transformations/ephys_compressors.py
aind_data_transfer/transformations/file_io.py
aind_data_transfer/transformations/flatfield_correction.py
aind_data_transfer/transformations/generic_compressors.py
aind_data_transfer/transformations/imaging_compressors.py
aind_data_transfer/transformations/metadata_creation.py
aind_data_transfer/transformations/ome_zarr.py
aind_data_transfer/util/__init__.py
aind_data_transfer/util/chunk_utils.py
aind_data_transfer/util/dask_utils.py
aind_data_transfer/util/env_utils.py
aind_data_transfer/util/file_utils.py
aind_data_transfer/util/io_utils.py
aind_data_transfer/util/npopto_correction.py
aind_data_transfer/util/s3_utils.py
aind_data_transfer/util/setup_logging.py
aind_data_transfer/writers/__init__.py
aind_data_transfer/writers/ephys_writers.py
aind_data_transfer/writers/imaging_writers.py
aind_data_transfer-0.35.3.dist-info/LICENSE
aind_data_transfer-0.35.3.dist-info/METADATA
aind_data_transfer-0.35.3.dist-info/WHEEL
aind_data_transfer-0.35.3.dist-info/top_level.txt
aind_data_transfer-0.35.3.dist-info/RECORD
