Metadata-Version: 2.1
Name: aind-data-transfer
Version: 0.35.3
Summary: Services for compression and transfer of aind-data to the cloud
License: MIT
Classifier: Programming Language :: Python :: 3
Requires-Python: >=3.9
License-File: LICENSE
Requires-Dist: pandas ==2.2.0
Requires-Dist: s3fs ==2024.3.1
Requires-Dist: s3transfer[crt] ==0.10.0
Requires-Dist: boto3[crt] ==1.34.51
Requires-Dist: numpy ==1.26.1
Requires-Dist: pyyaml ==6.0.1
Requires-Dist: google-cloud-storage ==2.12.0
Requires-Dist: pyminizip ==0.2.6
Requires-Dist: aind-codeocean-api >=0.4.0
Requires-Dist: aind-data-schema ==0.33.3
Requires-Dist: aind-metadata-service[client] >=0.2.5
Requires-Dist: tqdm ==4.64.1
Requires-Dist: aind-data-access-api[secrets] >=0.4.0
Requires-Dist: toml ==0.10.2
Requires-Dist: zarr ==2.17.2
Requires-Dist: numcodecs ==0.11.0
Provides-Extra: dev
Requires-Dist: aind-data-transfer[full] ; extra == 'dev'
Requires-Dist: black ; extra == 'dev'
Requires-Dist: coverage ; extra == 'dev'
Requires-Dist: flake8 ; extra == 'dev'
Requires-Dist: interrogate ; extra == 'dev'
Requires-Dist: isort ; extra == 'dev'
Requires-Dist: Sphinx ; extra == 'dev'
Provides-Extra: ephys
Requires-Dist: spikeinterface[full] >=0.100.5 ; extra == 'ephys'
Requires-Dist: probeinterface ==0.2.21 ; extra == 'ephys'
Requires-Dist: wavpack-numcodecs <=0.1.5,>=0.1.3 ; extra == 'ephys'
Provides-Extra: full
Requires-Dist: aind-data-transfer[ephys] ; extra == 'full'
Requires-Dist: aind-data-transfer[imaging] ; extra == 'full'
Provides-Extra: imaging
Requires-Dist: argschema ==3.0.4 ; extra == 'imaging'
Requires-Dist: dask ==2024.4.1 ; extra == 'imaging'
Requires-Dist: distributed ==2024.4.1 ; extra == 'imaging'
Requires-Dist: bokeh !=3.0.*,>=2.4.2 ; extra == 'imaging'
Requires-Dist: gcsfs ==2024.3.1 ; extra == 'imaging'
Requires-Dist: xarray-multiscale ==2.1.0 ; extra == 'imaging'
Requires-Dist: xarray ==2024.05.0 ; extra == 'imaging'
Requires-Dist: parameterized ==0.9.0 ; extra == 'imaging'
Requires-Dist: ome-zarr ==0.8.3 ; extra == 'imaging'
Requires-Dist: chardet ==5.1.0 ; extra == 'imaging'
Requires-Dist: natsort ==8.4.0 ; extra == 'imaging'
Requires-Dist: aind-ng-link ==1.0.15 ; extra == 'imaging'
